wheelspin/__init__.py
wheelspin/wheel_generator.py
wheelspin/wheelspin_lib.py
wheelspin_gif-1.0.0.dist-info/licenses/LICENSE
wheelspin_gif-1.0.0.dist-info/METADATA
wheelspin_gif-1.0.0.dist-info/WHEEL
wheelspin_gif-1.0.0.dist-info/top_level.txt
wheelspin_gif-1.0.0.dist-info/RECORD
