Metadata-Version: 2.4
Name: wheelspin-gif
Version: 1.0.0
Summary: Create beautiful animated spinning wheel GIFs for games, contests, and decision-making
Author-email: Mark Menzynski <mark.menzynski@example.com>
License: MIT
Project-URL: Homepage, https://github.com/mmenzyns/wheelspin-gif-python
Project-URL: Repository, https://github.com/mmenzyns/wheelspin-gif-python
Project-URL: Documentation, https://github.com/mmenzyns/wheelspin-gif-python#readme
Project-URL: Issues, https://github.com/mmenzyns/wheelspin-gif-python/issues
Keywords: wheel,gif,animation,game,decision,spinner,random
Classifier: Development Status :: 5 - Production/Stable
Classifier: Intended Audience :: Developers
Classifier: Programming Language :: Python :: 3
Classifier: Programming Language :: Python :: 3.8
Classifier: Programming Language :: Python :: 3.9
Classifier: Programming Language :: Python :: 3.10
Classifier: Programming Language :: Python :: 3.11
Classifier: Programming Language :: Python :: 3.12
Classifier: Topic :: Games/Entertainment
Classifier: Topic :: Multimedia :: Graphics
Classifier: Topic :: Software Development :: Libraries :: Python Modules
Requires-Python: >=3.8
License-File: LICENSE
Requires-Dist: pillow>=10.0.0
Dynamic: license-file
